ibhax/__init__.py
ibhax/decorators.py
ibhax-1.0.0.dist-info/LICENSE
ibhax-1.0.0.dist-info/METADATA
ibhax-1.0.0.dist-info/WHEEL
ibhax-1.0.0.dist-info/top_level.txt
ibhax-1.0.0.dist-info/RECORD
