Metadata-Version: 2.2
Name: ibhax
Version: 1.0.0
Summary: A comprehensive decorator toolkit with 100 production-grade decorators.
Home-page: https://github.com/ibhax/decorator_factory
Author: Albin Anthony
Author-email: albin.anthony.dev@gmail.com
Classifier: Programming Language :: Python :: 3
Classifier: License :: OSI Approved :: MIT License
Classifier: Operating System :: OS Independent
Requires-Python: >=3.6
License-File: LICENSE
Dynamic: author
Dynamic: author-email
Dynamic: classifier
Dynamic: description
Dynamic: description-content-type
Dynamic: home-page
Dynamic: requires-python
Dynamic: summary
